google_cloud_mldiagnostics/__init__.py
google_cloud_mldiagnostics/_version.py
google_cloud_mldiagnostics/api/__init__.py
google_cloud_mldiagnostics/api/metrics.py
google_cloud_mldiagnostics/api/mlrun.py
google_cloud_mldiagnostics/clients/__init__.py
google_cloud_mldiagnostics/clients/control_plane_client.py
google_cloud_mldiagnostics/clients/logging_client.py
google_cloud_mldiagnostics/commands/collect_profile.py
google_cloud_mldiagnostics/core/__init__.py
google_cloud_mldiagnostics/core/create_mlrun.py
google_cloud_mldiagnostics/core/global_manager.py
google_cloud_mldiagnostics/core/metrics.py
google_cloud_mldiagnostics/core/xprof.py
google_cloud_mldiagnostics/custom_types/__init__.py
google_cloud_mldiagnostics/custom_types/exceptions.py
google_cloud_mldiagnostics/custom_types/metric_types.py
google_cloud_mldiagnostics/custom_types/mlrun_types.py
google_cloud_mldiagnostics/utils/__init__.py
google_cloud_mldiagnostics/utils/config_utils.py
google_cloud_mldiagnostics/utils/gcp.py
google_cloud_mldiagnostics/utils/host_utils.py
google_cloud_mldiagnostics/utils/metric_utils.py
google_cloud_mldiagnostics/utils/orchestrator_utils.py
google_cloud_mldiagnostics/utils/run_phase_utils.py
google_cloud_mldiagnostics/utils/jax_utils/jax_config.py
google_cloud_mldiagnostics/utils/jax_utils/jax_host.py
google_cloud_mldiagnostics/utils/libtpu_utils/libtpu_metric.py
google_cloud_mldiagnostics-0.5.10.dist-info/licenses/LICENSE
google_cloud_mldiagnostics-0.5.10.dist-info/METADATA
google_cloud_mldiagnostics-0.5.10.dist-info/WHEEL
google_cloud_mldiagnostics-0.5.10.dist-info/top_level.txt
google_cloud_mldiagnostics-0.5.10.dist-info/RECORD
