Metadata-Version: 2.4
Name: google-cloud-mldiagnostics
Version: 0.5.10
Summary: diagnostic packages for profiling and ML experiment management
Author-email: Google Diagon++ <hypercompute-diagon@google.com>
License: Apache-2.0
Classifier: Programming Language :: Python :: 3.8
Classifier: Programming Language :: Python :: 3.9
Classifier: Programming Language :: Python :: 3.10
Classifier: Programming Language :: Python :: 3.11
Classifier: Programming Language :: Python :: 3.12
Requires-Python: >=3.8
License-File: LICENSE
Requires-Dist: google-api-core>=2.0.0
Requires-Dist: google-auth>=2.0.0
Requires-Dist: google-cloud-logging>=2.0.0
Requires-Dist: psutil>=6.0.0
Requires-Dist: packaging>=24.0
Dynamic: license-file
